_rostpy.cpython-310-x86_64-linux-gnu.so
rostpy.libs/libgcc_s-a04fdf82.so.1
rostpy.libs/libstdc++-a9383cce.so.6.0.28
rostpy-0.2.0.dist-info/RECORD
rostpy-0.2.0.dist-info/entry_points.txt
rostpy-0.2.0.dist-info/METADATA
rostpy-0.2.0.dist-info/LICENSE.txt
rostpy-0.2.0.dist-info/WHEEL
rostpy-0.2.0.dist-info/top_level.txt
rostpy/_version.py
rostpy/__init__.py
rostpy/utils.py
rostpy/bindings.cpp
rostpy/__main__.py
