Metadata-Version: 2.1
Name: rostpy
Version: 0.2.0
Summary: Python bindings for ROST
Home-page: https://gitlab.com/warplab/rostpy
Author: John San Soucie
Author-email: jsansoucie@whoi.edu
Maintainer: John San Soucie
Maintainer-email: jsansoucie@whoi.edu
License: MIT
Project-URL: Documentation, https://rostpy.readthedocs.io/
Project-URL: Bug Tracker, https://gitlab.com/warplab/rostpy/issues
Project-URL: Discussions, https://gitlab.com/warplab/rostpy/discussions
Project-URL: Changelog, https://gitlab.com/warplab/rostpy/releases
Platform: Any
Classifier: License :: OSI Approved :: MIT License
Classifier: Programming Language :: Python :: 3
Classifier: Programming Language :: Python :: 3 :: Only
Requires-Python: >=3.8
License-File: LICENSE.txt
Requires-Dist: click
Provides-Extra: dev
Requires-Dist: pre-commit >=2 ; extra == 'dev'
Requires-Dist: pytest >=6 ; extra == 'dev'
Provides-Extra: docs
Requires-Dist: Sphinx >=4.0 ; extra == 'docs'
Requires-Dist: myst-parser >=0.13 ; extra == 'docs'
Requires-Dist: sphinx-book-theme >=0.1.0 ; extra == 'docs'
Requires-Dist: sphinx-copybutton ; extra == 'docs'
Provides-Extra: test
Requires-Dist: pytest >=6 ; extra == 'test'
